lineoptim/__init__.py
lineoptim/components/__init__.py
lineoptim/components/line.py
lineoptim/components/network.py
lineoptim/plot/__init__.py
lineoptim/plot/graph.py
lineoptim/plot/plotter.py
lineoptim-1.2.0.dist-info/LICENCE
lineoptim-1.2.0.dist-info/METADATA
lineoptim-1.2.0.dist-info/WHEEL
lineoptim-1.2.0.dist-info/top_level.txt
lineoptim-1.2.0.dist-info/RECORD
