Metadata-Version: 2.1
Name: lineoptim
Version: 1.2.0
Summary: A line optimization package for electrical conductors.
Author: David Senoner
Author-email: david.senoner@gmail.com
Project-URL: Github, https://github.com/davidsenoner/lineoptim
Classifier: Development Status :: 3 - Alpha
Classifier: Intended Audience :: Developers
Classifier: License :: OSI Approved :: MIT License
Classifier: Programming Language :: Python :: 3
Classifier: Programming Language :: Python :: 3.8
Classifier: Programming Language :: Python :: 3.9
Classifier: Programming Language :: Python :: 3.10
License-File: LICENCE
Requires-Dist: matplotlib
Requires-Dist: numpy
Requires-Dist: pandas
Requires-Dist: torch
Requires-Dist: networkx
